catpandoc/__init__.py
catpandoc/__main__.py
catpandoc/application.py
catpandoc-2024.dist-info/entry_points.txt
catpandoc-2024.dist-info/LICENSE.md
catpandoc-2024.dist-info/METADATA
catpandoc-2024.dist-info/WHEEL
catpandoc-2024.dist-info/RECORD
