Metadata-Version: 2.1
Name: catpandoc
Version: 2024
Summary: Cat multiple document files to the terminal
Home-page: https://github.com/FHPythonUtils/CatPandoc
License: MIT
Author: FredHappyface
Requires-Python: >=3.8,<4.0
Classifier: Development Status :: 5 - Production/Stable
Classifier: Environment :: Console
Classifier: Intended Audience :: Developers
Classifier: Intended Audience :: Education
Classifier: License :: OSI Approved :: MIT License
Classifier: Natural Language :: English
Classifier: Operating System :: OS Independent
Classifier: Programming Language :: Python :: 3
Classifier: Programming Language :: Python :: 3.8
Classifier: Programming Language :: Python :: 3.9
Classifier: Programming Language :: Python :: 3.10
Classifier: Programming Language :: Python :: 3.11
Classifier: Programming Language :: Python :: 3.12
Classifier: Programming Language :: Python :: Implementation :: CPython
Classifier: Topic :: Software Development :: Libraries :: Python Modules
Classifier: Topic :: Text Processing
Classifier: Topic :: Utilities
Requires-Dist: pypandoc (>=1.12,<2)
Requires-Dist: rich (>=13.7.0,<14)
Project-URL: Documentation, https://github.com/FHPythonUtils/CatPandoc/blob/master/README.md
Project-URL: Repository, https://github.com/FHPythonUtils/CatPandoc
